{
  "db_name": "PostgreSQL",
  "query": "\n                INSERT INTO battle_records (match_id)\n                VALUES ($1)\n                RETURNING record_id\n                ",
  "describe": {
    "columns": [
      {
        "ordinal": 0,
        "name": "record_id",
        "type_info": "Int8"
      }
    ],
    "parameters": {
      "Left": [
        "Varchar"
      ]
    },
    "nullable": [
      false
    ]
  },
  "hash": "26ecd693a835dc3a20ee8167443261549384dbdca9494eb0e34667f0a210cdd6"
}
